neuron_ml/__init__.py
neuron_ml/core/__init__.py
neuron_ml/core/data/__init__.py
neuron_ml/core/data/createml.py
neuron_ml/core/data/tensorflow.py
neuron_ml/core/public/__init__.py
neuron_ml/core/public/classify.py
neuron_ml/core/public/clean.py
neuron_ml/core/public/export.py
neuron_ml/core/public/graph.py
neuron_ml/core/public/image.py
neuron_ml/core/public/labels.py
neuron_ml/core/public/load.py
neuron_ml/core/public/model.py
neuron_ml/core/public/train.py
neuron_ml/tools/__init__.py
neuron_ml/tools/subprocess_checker.py
neuron_ml-1.0.0.dist-info/METADATA
neuron_ml-1.0.0.dist-info/RECORD
neuron_ml-1.0.0.dist-info/WHEEL
neuron_ml-1.0.0.dist-info/top_level.txt
