Metadata-Version: 2.1
Name: neuron-ml
Version: 1.0.0
Summary: A tiny image classification library.
Home-page: https://github.com/arguiot/Neuron
Author: Arthur Guiot
Author-email: arguiot@gmail.com
License: UNKNOWN
Platform: UNKNOWN
Classifier: Programming Language :: Python :: 3
Classifier: License :: OSI Approved :: MIT License
Classifier: Operating System :: OS Independent
